<?xml version="1.0" encoding="UTF-8"?>
<vivadoHLSLog:LogRoot xmlns:vivadoHLSLog="www.xilinx.com/vivadoHLSLog">
  <errorLogs>
    <logs>
      <synLog/>
      <simLog/>
      <mgLog/>
      <packageLog/>
      <csimLog>
        <logs message="ERROR: [SIM 211-100] CSim failed with errors." projectName="transmitter" solutionName="solution1" date="2024-05-05T21:13:55.711-0700"/>
        <logs message="ERROR: [SIM 211-100] CSim failed with errors." projectName="transmitter" solutionName="solution1" date="2024-05-05T21:12:25.603-0700"/>
        <logs message="ERROR: [SIM 211-100] CSim failed with errors." projectName="transmitter" solutionName="solution1" date="2024-05-05T21:09:05.061-0700"/>
        <logs message="ERROR: [SIM 211-100] 'csim_design' failed: compilation error(s)." projectName="transmitter" solutionName="solution1" date="2024-05-05T21:08:09.841-0700"/>
        <logs message="ERROR: [SIM 211-100] CSim failed with errors." projectName="transmitter" solutionName="solution1" date="2024-05-05T21:03:50.885-0700"/>
        <logs message="ERROR: [SIM 211-100] CSim failed with errors." projectName="transmitter" solutionName="solution1" date="2024-05-05T21:02:23.736-0700"/>
        <logs message="ERROR: [SIM 211-100] CSim failed with errors." projectName="transmitter" solutionName="solution1" date="2024-05-05T20:59:05.269-0700"/>
        <logs message="ERROR: [SIM 211-100] 'csim_design' failed: compilation error(s)." projectName="transmitter" solutionName="solution1" date="2024-05-05T20:56:32.112-0700"/>
        <logs message="ERROR: [SIM 211-100] CSim failed with errors." projectName="transmitter" solutionName="solution1" date="2024-05-05T20:52:55.040-0700"/>
        <logs message="ERROR: [SIM 211-100] 'csim_design' failed: compilation error(s)." projectName="transmitter" solutionName="solution1" date="2024-05-05T20:48:49.203-0700"/>
        <logs message="ERROR: [SIM 211-100] CSim failed with errors." projectName="transmitter" solutionName="solution1" date="2024-05-05T20:46:15.736-0700"/>
        <logs message="ERROR: [SIM 211-100] 'csim_design' failed: compilation error(s)." projectName="transmitter" solutionName="solution1" date="2024-05-05T20:45:04.183-0700"/>
        <logs message="ERROR: [SIM 211-100] CSim failed with errors." projectName="transmitter" solutionName="solution1" date="2024-05-05T20:41:40.453-0700"/>
        <logs message="ERROR: [SIM 211-100] 'csim_design' failed: compilation error(s)." projectName="transmitter" solutionName="solution1" date="2024-05-05T20:40:28.184-0700"/>
        <logs message="ERROR: [SIM 211-100] 'csim_design' failed: compilation error(s)." projectName="transmitter" solutionName="solution1" date="2024-05-05T20:36:15.091-0700"/>
        <logs message="ERROR: [SIM 211-100] 'csim_design' failed: compilation error(s)." projectName="transmitter" solutionName="solution1" date="2024-05-05T20:34:30.244-0700"/>
        <logs message="ERROR: [SIM 211-100] 'csim_design' failed: compilation error(s)." projectName="transmitter" solutionName="solution1" date="2024-05-05T20:33:04.946-0700"/>
        <logs message="ERROR: [SIM 211-100] 'csim_design' failed: compilation error(s)." projectName="transmitter" solutionName="solution1" date="2024-05-05T20:31:14.990-0700"/>
        <logs message="ERROR: [SIM 211-100] 'csim_design' failed: compilation error(s)." projectName="transmitter" solutionName="solution1" date="2024-05-05T20:29:32.458-0700"/>
        <logs message="ERROR: [SIM 211-100] 'csim_design' failed: compilation error(s)." projectName="transmitter" solutionName="solution1" date="2024-05-05T20:27:34.542-0700"/>
        <logs message="ERROR: [SIM 211-100] 'csim_design' failed: compilation error(s)." projectName="transmitter" solutionName="solution1" date="2024-05-05T20:25:16.837-0700"/>
      </csimLog>
    </logs>
  </errorLogs>
  <warningLogs>
    <logs>
      <synLog>
        <logs message="WARNING: [RTGEN 206-101] Design contains AXI ports. Reset is fixed to synchronous and active low." projectName="transmitter" solutionName="solution1" date="2024-04-25T14:08:59.741-0700" type="Warning"/>
      </synLog>
      <simLog/>
      <mgLog/>
      <packageLog>
        <logs message="WARNING: [IP_Flow 19-4832] The IP name 'transmitter_sitofp_32s_32_6_no_dsp_1_ip' you have specified is long. The Windows operating system has path length limitations. It is recommended you use shorter names to reduce the likelihood of issues." projectName="transmitter" solutionName="solution1" date="2024-04-25T14:09:41.989-0700" type="Warning"/>
      </packageLog>
      <csimLog/>
    </logs>
  </warningLogs>
</vivadoHLSLog:LogRoot>
